<?xml version="1.0" encoding="UTF-8"?>
<liturgia>
    <ritual logia="Colmena No. 8" libro="1">    
        <seccion id="1" titulo="Apertura de Trabajos">
            <parte id="1" titulo="El Espacio Sagrado">
                <acto tipo="verso" actor="VM" tema="ﾂ｡Silencio en Logia, Hermanos (HH竏ｴ)! [Golpe de Mallete]"/>
                <acto tipo="verso" actor="VM" tema="Hermano Maestro de Ceremonias (MC竏ｴ), ﾂｿlos puestos estﾃ｡n cubiertos?"/>
                <acto tipo="verso" actor="MC" tema="Si, VM竏ｴ los puestos estﾃ｡n cubiertos y los HH竏ｴ prontos a iniciar los trabajos."/>
                <acto tipo="verso" actor="VM" tema="Hermano Primer Vigilante (1V竏ｴ): ﾂｿSois Masﾃｳn?"/>
                <acto tipo="verso" actor="1V" tema="Mis Hermanos (HH竏ｴ) me reconocen como tal, Venerable Maestro (VM竏ｴ)"/>
                <acto tipo="verso" actor="VM" tema="ﾂｿCuﾃ｡l es nuestro primer deber en Logia Hermano 1V竏ｴ?"/>
                <acto tipo="verso" actor="1V" tema="Ver si el templo estﾃ｡ cubierto de toda indiscreciﾃｳn profana"/>
                <acto tipo="verso" actor="VM" tema="Aseguraos de ello, Hermano mﾃｭo."/>
                <acto tipo="verso" actor="1V" tema="Hermano Guarda Templo (GT竏ｴ) Cumplid con vuestro deber. [El GT da tres golpes en la puerta y la respuesta externa es similar]"/>
                <acto tipo="verso" actor="GT" tema="Hermano 1V竏ｴ, el Temp竏ｴ estﾃ｡ a cubierto de toda indiscreciﾃｳn profana."/>
                <acto tipo="verso" actor="1V" tema="VM竏ｴ el Templo estﾃ｡ cubierto de toda indiscreciﾃｳn. (Da tres golpes de Mallete)"/>
            </parte>
            <parte id="2" titulo="El Cuerpo del Taller">
                <acto tipo="verso" actor="VM" tema="ﾂｿCuﾃ｡l es vuestro segundo deber en Hermano 1V竏ｴ?"/>
                <acto tipo="verso" actor="1V" tema="Ver si todos los HH竏ｴ que decoran ambas columnas son aprendices masones."/>
                <acto tipo="verso" actor="VM" tema="Aseguraos de ello, QQHH竏ｴ Primer y Segundo Vigilantes, de pie y al orden."/>
                <acto tipo="verso" actor="2V" tema="Hermano 1V竏ｴ, los HH竏ｴ que decoran mi Col竏ｴ son masones y estﾃ｡n de pie y al orden en el Grado de Aprendiz. [Da un golpe de mallete]"/>
                <acto tipo="verso" actor="1V" tema="VM竏ｴ los HH竏ｴ que se cobijan bajo la bﾃｳveda de nuestro templo son Masones y se hallan al orden, prontos para cumplir con vuestro mandato, y dispuestos a laborar en la construcciﾃｳn del Templo moral erigido a la ciencia, a la virtud y al trabajo. [Da un golpe de Mallete]."/>
                <acto tipo="verso" actor="VM" tema="HH竏ｴ mﾃｭos, tambiﾃｩn son masones los que decoran el Oriente, y estﾃ｡n prontos para trabajar en la construcciﾃｳn del Templo Moral que la Masonerﾃｭa eleva en la gloria del perfeccionamiento humano, mediante la conquista de los sublimes principios de Libertad, Igualdad y Fraternidad [Da un golpe de Mallete seguido por los Vigilantes]."/>
            </parte>
            <parte id="3" titulo="El Proposito del Cuerpo">
                <acto tipo="verso" actor="VM" tema="ﾂｿPara quﾃｩ ocupﾃ｡is ese puesto, Querido Hermano 2V竏ｴ?"/>
                <acto tipo="verso" actor="2V" tema="Para mejor observar el Sol en su meridiano, mandar a los obreros al trabajo y llamarlos a la recreaciﾃｳn, y de la recreaciﾃｳn al trabajo a fin de que la humanidad coseche el resplandor de los principios Masﾃｳnicos."/>
                <acto tipo="verso" actor="VM" tema="Querido Hermano 2V竏ｴ ﾂｿDonde toma asiento nuestro Querido Hermano 1V竏ｴ?"/>
                <acto tipo="verso" actor="2V" tema="Al occidente, VM竏ｴ."/>
                <acto tipo="verso" actor="VM" tema="ﾂｿPara quﾃｩ ocupﾃ｡is ese puesto Querido Hermano 1V竏ｴ?"/>
                <acto tipo="verso" actor="1V" tema="Asﾃｭ como el Sol se oculta en el Occidente al terminar el dﾃｭa, asﾃｭ se sienta aquﾃｭ el 1V竏ｴ, para ayudar al VM竏ｴ, abrir y cerrar la Logia, pagar a los obreros y despedirlos contentos y satisfechos de sus actos en la obra de amor y justicia en que estamos empeﾃｱados."/>
                <acto tipo="verso" actor="VM" tema="ﾂｿDonde toma asiento el VM竏ｴ Querido Hermano 1V竏ｴ?"/>
                <acto tipo="verso" actor="1V" tema="En el Oriente (Or竏ｴ)"/>
                <acto tipo="verso" actor="VM" tema="ﾂｿPara quﾃｩ H竏ｴ mﾃｭo."/>
                <acto tipo="verso" actor="1V" tema="Asﾃｭ como el Sol nace en Oriente al iniciar su carrera y romper el dﾃｭa, de igual manera se alza allﾃｭ el asiento del VM竏ｴ para abrir la Logia, dirigirla en sus trabajos e iluminar con sus luces, esclareciendo asﾃｭ los sublimes preceptos de nuestra."/>
            </parte>
            <parte id="4" titulo="La Experiencia del Cuerpo">
                <acto tipo="verso" actor="VM" tema="Querido Hermano 2V竏ｴ ﾂｿQuﾃｩ edad tenﾃｩis como Apr竏ｴ Mas竏ｴ?"/>
                <acto tipo="verso" actor="2V" tema="Tres aﾃｱos, VM竏ｴ."/>
                <acto tipo="verso" actor="VM" tema="ﾂｿA quﾃｩ hora empiezan los trabajos de Apr竏ｴ Mas竏ｴ, QH竏ｴ 1V竏ｴ?"/>
                <acto tipo="verso" actor="1V" tema="Al mediodﾃｭa, VM竏ｴ."/>
                <acto tipo="verso" actor="VM" tema="ﾂｿQuﾃｩ hora es, Querido Hermano 2V竏ｴ?"/>
                <acto tipo="verso" actor="2V" tema="La hora de empezar, mediodﾃｭa en punto, VM竏ｴ."/>
                <acto tipo="verso" actor="VM" tema="Siendo mediodﾃｭa en punto, hora que los Apr竏ｴ Mas竏ｴ abren sus trabajos QQHH竏ｴ, 1V竏ｴ y 2V竏ｴ, servios invitar a los obreros que decoran vuestras respectivas CCol竏ｴ, como yo a los de Oriente, para que se unan a vosotros y a mﾃｭ a fin de abrir los trabajos de esta Augusta y RL竏ｴ"/>
                <acto tipo="verso" actor="1V" tema="QH竏ｴ 2V竏ｴ y HH竏ｴ que decorﾃ｡is mi Col竏ｴ, por orden del VM竏ｴ, os invito que os unﾃ｡is a ﾃｩl y a mﾃｭ para abrir los trabajos de esta RL竏ｴ en el grado de Apr竏ｴ Mas竏ｴ."/>
                <acto tipo="verso" actor="2V" tema="QQHH竏ｴ de la Col竏ｴ del Norte, por orden del VM竏ｴ comunicada a mﾃｭ por nuestro QH竏ｴ 1V竏ｴ, que os unﾃ｡is a ﾃｩl y a nosotros para abrir los trabajos de esta RL竏ｴ en grado de Apr竏ｴMas竏ｴ. [Anunciado en mi Col竏ｴ, QH竏ｴ 1V竏ｴ.]"/>
                <acto tipo="verso" actor="1V" tema="Anunciado en ambas CCol竏ｴ, VM竏ｴ."/>
            </parte>
            <parte id="5" titulo="La Consagraciﾃｳn de la Luz">
                <acto tipo="verso" actor="VM" tema="ﾂ｡En pie y al Orden, Queridos Hermanos! [Da un golpe de Mallete seguido por los Vigilantes]."/>
                <acto tipo="verso" actor="VM" tema="QH竏ｴ Maestro de Ceremonias (MC竏ｴ) , prended las Luces. (MC竏ｴ , abre el Libro de la Ley y coloca la Escuadra y sobre esta el Compﾃ｡s. Enciende la estrella del VM竏ｴ, dice: ﾂ｡Que la Sabidurﾃｭa guie nuestros trabajos! ; MC竏ｴ, enciende la estrella del 1V竏ｴ VM竏ｴ, dice: ﾂ｡Que la Fuerza los sostenga! ; MC竏ｴ, enciende la estrella del 2V竏ｴ, VM竏ｴ dice: ﾂ｡Que la Belleza los adorne!)"/>
                <acto tipo="verso" actor="VM" tema="Puesto que todo estﾃ｡ justo y perfecto, y que es la hora que los AAp竏ｴ MMas竏ｴ empiezan sus trabajos, unﾃｭos a mﾃｭ HH竏ｴ mﾃｭos, ALGDGADU竏ｴ y en su nombre y bajo la obediencia de la Ser竏ｴ Gran L竏ｴ de Lengua Espaﾃｱola para los EE. UU. de A., declaro abiertos los trabajos de esta RL竏ｴ en el grado de Ap竏ｴMas竏ｴ del REAA竏ｴ. Queda prohibido a todo H竏ｴ pasar de una a otra Col竏ｴ ni cubrir el Templo sin permiso de su respectivo V竏ｴ; ni tratar asuntos polﾃｭticos ni religiosos, a mﾃｭ HH竏ｴ por el signo y Bat竏ｴ de Grado. [Da tres golpes de Mall竏ｴ que repiten los VV竏ｴ] Tomad asiento, QQHH竏ｴ."/>
            </parte>
        </seccion>
        <seccion id="2" titulo="Desarrollo de Trabajos">        
            <parte id="1" titulo="Del Balaustre del la Sesiﾃｳn Anterior">
                <acto tipo="verso" actor="VM" tema="QQHH竏ｴ, habiﾃｩndose cumplido con las formalidades de la apertura, entramos ahora en el Desarrollo de Trabajos."/>
                <acto tipo="verso" actor="VM" tema="QH竏ｴ Secretario (Sec竏ｴ), servﾃｭos dar lectura del ﾃｺltimo Trazado de este logia."/>
                <acto tipo="verso" actor="Sec" tema="[QH竏ｴ Sec竏ｴ procede con la lectura.] [[INSTANCIA]]"/>
                <acto tipo="verso" actor="1V" tema="Reina el silencio en ambas CCol竏ｴ, VM竏ｴ."/>
                <acto tipo="verso" actor="VM" tema="QQHH竏ｴ 1V竏ｴ y 2V竏ｴ, anunciad en vuestras respectivas columnas que el memo estﾃ｡ en discusiﾃｳn. Si algﾃｺn hermano desea hacer una observaciﾃｳn, tiene la palabra"/>
                <acto tipo="verso" actor="1V" tema="QH竏ｴ 2V竏ｴ, HH竏ｴ de la Col竏ｴ del Norte, el trazado de la sesiﾃｳn anterior estﾃ｡ en discusiﾃｳn por orden del VM竏ｴ."/>
                <acto tipo="verso" actor="2V" tema="HH竏ｴ de la Col竏ｴ del Sur, el trazado estﾃ｡ en discusiﾃｳn. La palabra es vuestra."/>
                <acto tipo="verso" actor="VM" tema="Habiendo agotado los asuntos administrativos del Desarrollo de Trabajos, pasemos ahora a la instrucciﾃｳn del Grado.."/>       
                <acto tipo="verso" actor="VM" tema="QQHH竏ｴ 1V竏ｴ y 2V竏ｴ, anunciad en vuestras respectivas CCol竏ｴ que se darﾃ｡ lectura a la Plancha de los ﾃｺltimos trabajos."/>
                <acto tipo="verso" actor="VM" tema="QQHH竏ｴ 1V竏ｴ y 2V竏ｴ, anunciad en vuestras respectivas CCol竏ｴ, como yo lo hago en Ort竏ｴ que estﾃ｡ en consideraciﾃｳn la plancha trazada por nuestro QH竏ｴ Sec竏ｴ, en tal sentido, si algﾃｺn H竏ｴ desea hacer uso de la palabra podﾃｩis concedﾃｩrsela."/>
                <acto tipo="verso" actor="2V" tema="Reina el silencio en mi Columna Hermano 1V竏ｴ."/>
                <acto tipo="verso" actor="1V" tema="Reina el silencio en ambas CCol竏ｴ, VM竏ｴ."/>
                <acto tipo="verso" actor="VM" tema="QH竏ｴ OF竏ｴ ﾂｿQuerﾃｩis darnos vuestras conclusiones respecto a la plancha trazada por nuestro H竏ｴ Sec竏ｴ de nuestros ﾃｺltimos trabajos? [El H竏ｴOra竏ｴ da las conclusiones]"/>
                <acto tipo="verso" actor="VM" tema="Despuﾃｩs de las conclusiones del H竏ｴ Ora竏ｴ, los HH竏ｴ que estﾃｩn de acuerdo se servirﾃ｡n de hacer la seﾃｱal de aprobaciﾃｳn al primer golpe de Mall竏ｴ. (Con golpe de Mallete.) "/>
                <acto tipo="verso" actor="VM" tema="ﾂ｡Hermanos mﾃｭos! El logia ha ordenado nuestro primer tiempo; ahora, para que el espﾃｭritu se manifieste en nueva forma, vamos a cubrir los trabajos de este Grado y proceder a . [Con golpe de Mallete.] [[INSTANCIA]]"/>
            </parte>          
        </seccion>            
        <seccion id="3" titulo="Clausura de Trabajos">
             <parte id="1" titulo="Del Tronco de Beneficencia">
                <acto tipo="verso" actor="VM" tema="QQHH竏ｴ 1V竏ｴ y 2V竏ｴ anunciad en vuestras CCol竏ｴ que el H竏ｴ Hos竏ｴ va a circular en tronco de beneficencia."/>
                <acto tipo="verso" actor="2V" tema="Anunciado en la Col竏ｴ del Mediodﾃｭa, H竏ｴ 1V竏ｴ."/>
                <acto tipo="verso" actor="1V" tema="Anunciado en ambas Ccol竏ｴ, VM竏ｴ."/>
                <acto tipo="verso" actor="VM" tema="QH竏ｴ Hos竏ｴ, cumplid con vuestro deber. [El H竏ｴ Hos竏ｴ se coloca entre Ccol竏ｴ.]."/>
                <acto tipo="verso" actor="1V" tema="VM竏ｴ, el H竏ｴ Hos竏ｴ se encuentra entre Ccol竏ｴ pronto a circular entre los HH竏ｴ."/>
                <acto tipo="verso" actor="VM" tema="Ordenad que circule empezando por la derecha."/>
                <acto tipo="verso" actor="1V" tema="QH竏ｴ Hos竏ｴ, cumplid con vuestro deber. (El H竏ｴ Hos竏ｴ despuﾃｩs de haber circulado se coloca entre Ccol竏ｴ.)"/>
                <acto tipo="verso" actor="Hos" tema="QH竏ｴ 1V竏ｴ, he cumplido vuestro mandato."/>
                <acto tipo="verso" actor="1V" tema="VM竏ｴ, el tronco de beneficencia despuﾃｩs de circular por los cuatro puntos cardinales del templo se encuentra nuevamente entre Ccol竏ｴ.."/>
                <acto tipo="verso" actor="VM" tema="Ordenad que ocupe su puesto y nos de cuenta de su contenido."/>
                <acto tipo="verso" actor="VM" tema="QH竏ｴ OF竏ｴ, ﾂｿNos querﾃｩis dar las conclusiones de los trabajos de la Ten竏ｴ de hoy?"/>
                <acto tipo="verso" actor="OF" tema="(Da a conocer el resultado del Trazado)."/>
                <acto tipo="verso" actor="VM" tema="En virtud de haber sido en un todo favorable las conclusiones del H竏ｴ OF竏ｴ a la labor realizada, vamos a proceder al cierre de los trabajos de esta RL竏ｴ."/>
                <acto tipo="verso" actor="VM" tema="QH竏ｴ 1V竏ｴ podﾃｩis decirnos. ﾂｿCuﾃ｡les son los caracteres distintivos que deben de adornar al verdadero Mas竏ｴ?"/>
                <acto tipo="verso" actor="1V" tema="Ser virtuoso y amante con los HH竏ｴ y tolerante con todos."/>
                <acto tipo="verso" actor="VM" tema="QH竏ｴ 2V竏ｴ ﾂｿQuﾃｩ se deben los Masones entre sﾃｭ?"/>
                <acto tipo="verso" actor="2V" tema="Respeto mutuo y amor fraternal, VM竏ｴ."/>
                <acto tipo="verso" actor="VM" tema="ﾂｿCuﾃ｡l debe ser la conducta del Masﾃｳn en el mundo profano, QH竏ｴ 1V竏ｴ?"/>
                <acto tipo="verso" actor="1V" tema="Enseﾃｱar con la prﾃ｡ctica el ejercicio de las virtudes."/>
            </parte>    
            <parte id="2" titulo="De la Verificaciﾃｳn de los Trabajos">
                <acto tipo="verso" actor="VM" tema="QH竏ｴ 1V竏ｴ ﾂｿQuﾃｩ edad tenﾃｩis como Ap竏ｴMas竏ｴ?"/>
                <acto tipo="verso" actor="1V" tema="Tres aﾃｱos, VM竏ｴ."/>
                <acto tipo="verso" actor="VM" tema="QH竏ｴ 2V竏ｴ ﾂｿA quﾃｩ hora cierran los trabajos los AAp竏ｴ Mas竏ｴ?"/>
                <acto tipo="verso" actor="2V" tema="Medianoche en punto, VM竏ｴ."/>
                <acto tipo="verso" actor="VM" tema="ﾂｿQuﾃｩ hora es, QH竏ｴ 1V竏ｴ?"/>
                <acto tipo="verso" actor="1V" tema="La hora de cerrar, medianoche en punto, VM竏ｴ."/>
            </parte>     
            <parte id="3" titulo="Del Cierre de los Trabajos">    
                <acto tipo="verso" actor="VM" tema="Puesto que es la hora en que los AAp竏ｴ MMas竏ｴ cierran sus trabajos, QQHH竏ｴ 1V竏ｴ y 2V竏ｴ, invitad a los obreros de vuestras respectivas CCol竏ｴ como yo invito a los de Or竏ｴ para que se unan a vosotros y a mﾃｭ a fin de cerrar los trabajos de esta Aug竏ｴ RL竏ｴ. [El VM竏ｴ da tres golpes de Mall竏ｴ que repiten los VV竏ｴ y dice: de pie y al orden mis HH竏ｴ.]."/>
                <acto tipo="verso" actor="2V" tema="Todo estﾃ｡ justo y perfecto, VM竏ｴ."/>
                <acto tipo="verso" actor="1V" tema="Reina completa armonﾃｭa, VM竏ｴ y estamos en condiciﾃｳn de luchar por la emancipaciﾃｳn Moral y Material de los seres humanos."/>
                <acto tipo="verso" actor="VM" tema="Ya Hermanos mﾃｭos: puesto que todo es justo y perfecto, y nos hallamos en condiciﾃｳn de luchar para que el estandarte de la Justicia ondee desde la cﾃｺpula de nuestros Templos sobre toda la humanidad, acompaﾃｱadme a clausurar las tareas de esta Respetable Logia. ALGDGADU竏ｴ, en su nombre y bajo la obediencia de la Ser竏ｴ Gr竏ｴ L竏ｴ de Lengua Espaﾃｱola para los EE. UU. de A., declaro cerrados los trabajos de este logia por el dﾃｭa de hoy. ﾂ｡A mﾃｭ, Hermanos, con el Signo y la Baterﾃｭa de Grado!"/>
                <acto tipo="verso" actor="VM" tema="Queridos Hermanos, antes de partir: ﾂｿJurﾃ｡is guardar absoluto silencio sobre lo aquﾃｭ visto y oﾃｭdo, incluso ante aquellos Hermanos que no asistieron a esta Tenida? Todos. ﾂ｡Lo juramos!"/>
                <acto tipo="verso" actor="VM" tema="Si asﾃｭ lo hiciereis, que el GADU竏ｴ os lo premie; si no, que ﾃ瑛 os lo demande. H竏ｴ MC竏ｴ servﾃｭos cerrar el Ara. Hermanos mﾃｭos, retirﾃｩmonos en paz y fraternidad."/>
                <acto tipo="verso" actor="MC" tema="[Apaga la estrella de 2V竏ｴ , Apaga la estrella del 1V竏ｴ y Apaga la estrella del VM竏ｴ Retira la Escuadra y el Compﾃ｡s, y cierra el Libro de la Ley]"/>
            </parte>
        </seccion>
        <seccion id="4" titulo="Proposiciones por Escrito">
            <parte id="1" titulo="De las Proposiciones por Escrito">
                <acto tipo="verso" actor="VM" tema="QQHH竏ｴ 1V竏ｴ y 2V竏ｴ anunciad a los HH竏ｴ de vuestras respectivas CCol竏ｴ como yo lo hago en el Or竏ｴ que nuestro Q竏ｴH竏ｴ M竏ｴ de Cer竏ｴ va a circular el saco de proposiciones. [El MC竏ｴ cumple con su deber y se coloca entre CCol竏ｴ.]"/>
                <acto tipo="verso" actor="1V" tema="VM竏ｴ, el saco de proposiciones se encuentra entre CCol竏ｴ para circular."/>
                <acto tipo="verso" actor="VM" tema="Ordenad que circule empezando por mi derecha."/>
                <acto tipo="verso" actor="1V" tema="He cumplido con mi deber."/>
                <acto tipo="verso" actor="1V" tema="VM竏ｴ, el saco de proposiciones, despuﾃｩs de haber circulado por los cuatro puntos cardinales, se halla nuevamente entre CCol竏ｴ."/>
                <acto tipo="verso" actor="VM" tema="Ordenad que pase a Or竏ｴ y que en compaﾃｱﾃｭa del H竏ｴ Ora竏ｴ nos enteremos de su contenido."/>
                <acto tipo="verso" actor="VM" tema="QQHH竏ｴ 1V竏ｴ y 2V竏ｴ anunciad en vuestras respectivas CCol竏ｴ que vamos a pasar a proposiciones verbales."/>
                <acto tipo="verso" actor="2V" tema="H竏ｴ 1V竏ｴ, reina el silencio en mi Col竏ｴ."/>
                <acto tipo="verso" actor="1V" tema="VM竏ｴ, reina silencio en ambas CCol竏ｴ."/>
                <acto tipo="verso" actor="VM" tema="QQHH竏ｴ 1V竏ｴ y 2V竏ｴ anunciad a los HH竏ｴ de vuestras respectivas CCol竏ｴ que voy a conceder la palabra en bien general de la orden y en particular de este Tall竏ｴ."/>
                <acto tipo="verso" actor="2V" tema="QH竏ｴ de la Col竏ｴ del Norte, por orden del VM竏ｴ y transmitida a mﾃｭ por el QH竏ｴ 1V竏ｴ que estﾃ｡ concedida la palabra en bien general de la orden y particular de este Tall竏ｴ."/>
                <acto tipo="verso" actor="2V" tema="QH竏ｴ 1V竏ｴ, reina el silencio en mi Col竏ｴ.."/>
                <acto tipo="verso" actor="1V" tema="VM竏ｴ, reina silencio en ambas CCol竏ｴ."/>
            </parte>
        </seccion>    
        <seccion id="5" titulo="Asuntos Familiares y Otros">
            <parte id="1" titulo="De los Asuntos Familiares y Otros">
                <acto tipo="verso" actor="VM" tema="QQHH竏ｴ 1V竏ｴ y 2V竏ｴ anunciad a los HH竏ｴ de vuestras respectivas CCol竏ｴ como yo lo hago en el Or竏ｴ que vamos a tratar asuntos familiares."/>
                <acto tipo="verso" actor="VM" tema="Invitad al MC竏ｴ.. a que dﾃｩ un paseo al salﾃｳn de actos perdidos a ver si hay algﾃｺn visitante."/>
            </parte>
        </seccion>
        <seccion id="6" titulo="Instrucciﾃｳn: Simbolismo">
            <parte id="1" titulo="Estudio Profundo">
                <acto tipo="verso" actor="Ora" tema="La Piedra Bruta representa el estado de imperfecciﾃｳn..."/>
                <acto tipo="verso" actor="Ora" tema="Es cuanto, VM竏ｴ."/>
            </parte>
        </seccion>
        <seccion id="7" titulo="Logia de San Juan">
            <parte id="1" titulo="Estudio Profundo">
                <acto tipo="verso" actor="Ora" tema="La Piedra Bruta representa el estado de imperfecciﾃｳn..."/>
                <acto tipo="verso" actor="Ora" tema="Es cuanto, VM竏ｴ"/>
            </parte>
        </seccion>
    </ritual>
    <ritual logia="Colmena No. 8" libro="2">
        <seccion id="1" titulo="Apertura de Trabajos">
            <parte id="1" titulo="Apertura de Trabajos">
                <acto tipo="verso" actor="VM" tema="HH竏ｴ 1V竏ｴ y 2V竏ｴ Servios anunciar alo HH竏ｴ de vuestras respectivas columnas, como yo lo hago en el Or竏ｴ que voy a suspender los trabajos con un solo golpe de Mall竏ｴ para abrir la de Compaﾃｱero."/>
                <acto tipo="verso" actor="1V" tema="H竏ｴ 2V竏ｴ y HH竏ｴ de mi columna, nuestro VM竏ｴ va a suspender los trabajos por un solo golpe de Mall竏ｴ"/>
                <acto tipo="verso" actor="2V" tema="HH竏ｴ de la Col竏ｴ del Sur os anuncio que el VM竏ｴ va a suspender los Trbajos con un solo golpe de Mall竏ｴ"/>
                <acto tipo="verso" actor="1V" tema="Anunciado VM竏ｴ"/>
                <acto tipo="verso" actor="VM" tema="[Da un golpe de Maellete]... y clausura los trabajos invitando a los HH竏ｴ Aprendices a que cubran el Tempo"/>
            </parte>
        </seccion>
         <seccion id="2" titulo="Cﾃ｡mara de Compaﾃｱeros">
            <parte id="1" titulo="Inicio de Trabajos">
                <acto tipo="verso" actor="VM" tema="Servios H竏ｴ GT竏ｴ avisar al H竏ｴ GTE竏ｴ que voy a abrir la Log竏ｴ en el Grado de Compaﾃｱero y que vigile en consecuencia."/>
                <acto tipo="verso" actor="GT" tema="Seguimos a cubierto y el GTE竏ｴ esta avisado Muy VM竏ｴ"/>
                <acto tipo="verso" actor="VM" tema="H竏ｴ 1V竏ｴ ﾂｿCuﾃ｡l es el primer deber de un Vigilante en Cﾃ｡mara de Compaﾃｱeros?"/>
                <acto tipo="verso" actor="1V" tema="Asegurarse que el Templo estﾃｩ cubierto de las indiscreciones de profanos y Aprendices."/>
                <acto tipo="verso" actor="VM" tema="Aseguraos de ello, querido hermano"/>
            </parte>
        </seccion>
    </ritual>
        <ritual logia="Colmena No. 8" libro="3">
        <seccion id="1" titulo="Logia de San Juan">
            <parte id="1" titulo="Estudio Profundo">
                <acto tipo="verso" actor="VM" tema="La Piedra Bruta representa el estado de imperfecciﾃｳn..."/>
                <acto tipo="verso" actor="VM" tema="Es cuanto, VM竏ｴ."/>
            </parte>
        </seccion>
    </ritual>
</liturgia>
