{
  "oficiales": [
    { "id": "VM", "nombre": "Venerable Maestro" },
    { "id": "1V", "nombre": "Primer Vigilante" },
    { "id": "2V", "nombre": "Segundo Vigilante" },
    { "id": "OF", "nombre": "Orador Fiscal" },
    { "id": "MC", "nombre": "Maestro de Ceremonias" },
    { "id": "GT", "nombre": "Guarda Templo" },
    { "id": "Sec", "nombre": "Secretario" },    
    { "id": "Hos", "nombre": "Hospitalario" }
  ],
  "definiciones": {
    "VM‚ąī": "Venerable Maestro",
    "1V‚ąī": "Primer Vigilante",
    "2V‚ąī": "Segundo Vigilante",
    "HH‚ąī": "Hermanos",   
    "RL‚ąī": "Respetable Logia",
    "GADU‚ąī": "Gran Arquitecto Del Universo",
    "QQHH‚ąī": "Queridos Hermanos",
    "ALGDGADU‚ąī": "A la Gloria del Gran Arquitecto Del Universo"
  }
}
